refactorio/__init__.py
refactorio/cli.py
refactorio/config_manager.py
refactorio/file_manager.py
refactorio-0.1.6.dist-info/entry_points.txt
refactorio-0.1.6.dist-info/METADATA
refactorio-0.1.6.dist-info/WHEEL
refactorio-0.1.6.dist-info/RECORD
