Metadata-Version: 2.1
Name: refactorio
Version: 0.1.6
Summary: CLI tool for managing Ruff, Black, and pre-commit.
License: Proprietary
Author: Кузьмин Влад Валерьевич
Author-email: vlad.kuzmin@simbirsoft.com
Requires-Python: >=3.11,<4.0
Classifier: License :: Other/Proprietary License
Classifier: Programming Language :: Python :: 3
Classifier: Programming Language :: Python :: 3.11
Classifier: Programming Language :: Python :: 3.12
Classifier: Programming Language :: Python :: 3.13
Requires-Dist: pre-commit (>=4.1.0,<5.0.0)
Requires-Dist: rich (>=13.9.4,<14.0.0)
Requires-Dist: toml (>=0.10.2,<0.11.0)
Requires-Dist: tomlkit (>=0.13.2,<0.14.0)
Requires-Dist: typer (>=0.15.2,<0.16.0)
